cloudeasy/__init__.py
cloudeasy/alicloud/__init__.py
cloudeasy/alicloud/alicloud_config.py
cloudeasy/alicloud/dns_manager.py
cloudeasy/alicloud/resource_center_manager.py
cloudeasy/alicloud/security_group_manager.py
cloudeasy/alicloud/tea_api.py
cloudeasy/github/__init__.py
cloudeasy/github/gh_app_oauth.py
cloudeasy/github/manager/__init__.py
cloudeasy/github/manager/secret.py
cloudeasy/github/manager/user.py
cloudeasy/github/session.py
cloudeasy/sugar/__init__.py
cloudeasy/sugar/intersect.py
cloudeasy/sugar/retry.py
cloudeasy-0.2.2.dist-info/METADATA
cloudeasy-0.2.2.dist-info/WHEEL
cloudeasy-0.2.2.dist-info/RECORD
